{
  "fio version" : "fio-3.8",
  "timestamp" : 1534558743,
  "timestamp_ms" : 1534558743033,
  "time" : "Sat Aug 18 02:19:03 2018",
  "global options" : {
    "offset" : "78713454592"
  },
  "jobs" : [
    {
      "jobname" : "wdpc",
      "groupid" : 0,
      "error" : 0,
      "eta" : 0,
      "elapsed" : 61,
      "job options" : {
        "ioengine" : "libaio",
        "group_reporting" : "1",
        "direct" : "1",
        "rw" : "readwrite",
        "bs" : "1024KB",
        "numjobs" : "1",
        "iodepth" : "32",
        "size" : "75%",
        "name" : "wdpc",
        "rwmixread" : "100",
        "time_based" : "1",
        "runtime" : "60s",
        "filename" : "/dev/sda"
      },
      "read" : {
        "io_bytes" : 26238517248,
        "io_kbytes" : 25623552,
        "bw_bytes" : 436748127,
        "bw" : 426511,
        "iops" : 416.515472,
        "runtime" : 60077,
        "total_ios" : 25023,
        "short_ios" : 0,
        "drop_ios" : 0,
        "slat_ns" : {
          "min" : 159834,
          "max" : 19476625,
          "mean" : 467582.979099,
          "stddev" : 251838.156357
        },
        "clat_ns" : {
          "min" : 11681542,
          "max" : 148170750,
          "mean" : 76320771.058466,
          "stddev" : 2531331.512560,
          "percentile" : {
            "1.000000" : 74973184,
            "5.000000" : 76021760,
            "10.000000" : 76021760,
            "20.000000" : 76021760,
            "30.000000" : 76021760,
            "40.000000" : 76021760,
            "50.000000" : 76021760,
            "60.000000" : 76021760,
            "70.000000" : 76021760,
            "80.000000" : 76021760,
            "90.000000" : 76021760,
            "95.000000" : 77070336,
            "99.000000" : 77070336,
            "99.500000" : 79167488,
            "99.900000" : 101187584,
            "99.950000" : 119013376,
            "99.990000" : 143654912
          },
          "bins" : {
            "11730944" : 1,
            "12124160" : 1,
            "12648448" : 1,
            "13041664" : 1,
            "13303808" : 1,
            "13434880" : 1,
            "13828096" : 1,
            "15138816" : 1,
            "16908288" : 1,
            "18743296" : 1,
            "20316160" : 1,
            "22413312" : 1,
            "23986176" : 1,
            "25821184" : 1,
            "27656192" : 1,
            "29491200" : 1,
            "31326208" : 1,
            "33161216" : 1,
            "34865152" : 1,
            "36962304" : 1,
            "39059456" : 1,
            "41680896" : 1,
            "43778048" : 1,
            "45875200" : 1,
            "46399488" : 1,
            "47972352" : 1,
            "48496640" : 1,
            "49545216" : 2,
            "50069504" : 1,
            "51118080" : 2,
            "52690944" : 2,
            "53215232" : 1,
            "54263808" : 1,
            "54788096" : 4,
            "56360960" : 1,
            "56885248" : 3,
            "57409536" : 1,
            "58458112" : 5,
            "58982400" : 2,
            "59506688" : 1,
            "60030976" : 2,
            "60555264" : 3,
            "61079552" : 1,
            "61603840" : 3,
            "62128128" : 5,
            "63176704" : 1,
            "63700992" : 2,
            "64225280" : 6,
            "65273856" : 2,
            "65798144" : 3,
            "66322432" : 4,
            "66846720" : 3,
            "67633152" : 8,
            "68681728" : 4,
            "69730304" : 5,
            "70778880" : 6,
            "71827456" : 10,
            "72876032" : 15,
            "73924608" : 25,
            "74973184" : 384,
            "76021760" : 22986,
            "77070336" : 1334,
            "78118912" : 29,
            "79167488" : 14,
            "80216064" : 12,
            "81264640" : 5,
            "82313216" : 5,
            "83361792" : 5,
            "84410368" : 7,
            "85458944" : 5,
            "86507520" : 6,
            "87556096" : 4,
            "88604672" : 8,
            "89653248" : 3,
            "90701824" : 5,
            "91750400" : 5,
            "92798976" : 2,
            "93847552" : 4,
            "94896128" : 1,
            "95944704" : 4,
            "96993280" : 2,
            "98041856" : 2,
            "99090432" : 3,
            "100139008" : 1,
            "101187584" : 2,
            "102236160" : 2,
            "103284736" : 1,
            "104333312" : 1,
            "105381888" : 2,
            "107479040" : 1,
            "109576192" : 1,
            "112721920" : 1,
            "114819072" : 1,
            "116916224" : 1,
            "119013376" : 1,
            "122159104" : 1,
            "124256256" : 1,
            "126353408" : 1,
            "129499136" : 1,
            "131596288" : 1,
            "133693440" : 1,
            "135266304" : 1,
            "139460608" : 1,
            "141557760" : 1,
            "143654912" : 1,
            "145752064" : 1,
            "147849216" : 1
          }
        },
        "lat_ns" : {
          "min" : 12284708,
          "max" : 148693125,
          "mean" : 76792736.141310,
          "stddev" : 2513128.372758
        },
        "bw_min" : 423089,
        "bw_max" : 428032,
        "bw_agg" : 99.990493,
        "bw_mean" : 426470.450000,
        "bw_dev" : 949.736619,
        "bw_samples" : 120,
        "iops_min" : 413,
        "iops_max" : 418,
        "iops_mean" : 416.466667,
        "iops_stddev" : 0.934253,
        "iops_samples" : 120
      },
      "write" : {
        "io_bytes" : 0,
        "io_kbytes" : 0,
        "bw_bytes" : 0,
        "bw" : 0,
        "iops" : 0.000000,
        "runtime" : 0,
        "total_ios" : 0,
        "short_ios" : 0,
        "drop_ios" : 0,
        "slat_ns" : {
          "min" : 0,
          "max" : 0,
          "mean" : 0.000000,
          "stddev" : 0.000000
        },
        "clat_ns" : {
          "min" : 0,
          "max" : 0,
          "mean" : 0.000000,
          "stddev" : 0.000000,
          "percentile" : {
            "1.000000" : 0,
            "5.000000" : 0,
            "10.000000" : 0,
            "20.000000" : 0,
            "30.000000" : 0,
            "40.000000" : 0,
            "50.000000" : 0,
            "60.000000" : 0,
            "70.000000" : 0,
            "80.000000" : 0,
            "90.000000" : 0,
            "95.000000" : 0,
            "99.000000" : 0,
            "99.500000" : 0,
            "99.900000" : 0,
            "99.950000" : 0,
            "99.990000" : 0
          },
          "bins" : {

          }
        },
        "lat_ns" : {
          "min" : 0,
          "max" : 0,
          "mean" : 0.000000,
          "stddev" : 0.000000
        },
        "bw_min" : 0,
        "bw_max" : 0,
        "bw_agg" : 0.000000,
        "bw_mean" : 0.000000,
        "bw_dev" : 0.000000,
        "bw_samples" : 0,
        "iops_min" : 0,
        "iops_max" : 0,
        "iops_mean" : 0.000000,
        "iops_stddev" : 0.000000,
        "iops_samples" : 0
      },
      "trim" : {
        "io_bytes" : 0,
        "io_kbytes" : 0,
        "bw_bytes" : 0,
        "bw" : 0,
        "iops" : 0.000000,
        "runtime" : 0,
        "total_ios" : 0,
        "short_ios" : 0,
        "drop_ios" : 0,
        "slat_ns" : {
          "min" : 0,
          "max" : 0,
          "mean" : 0.000000,
          "stddev" : 0.000000
        },
        "clat_ns" : {
          "min" : 0,
          "max" : 0,
          "mean" : 0.000000,
          "stddev" : 0.000000,
          "percentile" : {
            "1.000000" : 0,
            "5.000000" : 0,
            "10.000000" : 0,
            "20.000000" : 0,
            "30.000000" : 0,
            "40.000000" : 0,
            "50.000000" : 0,
            "60.000000" : 0,
            "70.000000" : 0,
            "80.000000" : 0,
            "90.000000" : 0,
            "95.000000" : 0,
            "99.000000" : 0,
            "99.500000" : 0,
            "99.900000" : 0,
            "99.950000" : 0,
            "99.990000" : 0
          },
          "bins" : {

          }
        },
        "lat_ns" : {
          "min" : 0,
          "max" : 0,
          "mean" : 0.000000,
          "stddev" : 0.000000
        },
        "bw_min" : 0,
        "bw_max" : 0,
        "bw_agg" : 0.000000,
        "bw_mean" : 0.000000,
        "bw_dev" : 0.000000,
        "bw_samples" : 0,
        "iops_min" : 0,
        "iops_max" : 0,
        "iops_mean" : 0.000000,
        "iops_stddev" : 0.000000,
        "iops_samples" : 0
      },
      "sync" : {
        "lat_ns" : {
          "min" : 0,
          "max" : 0,
          "mean" : 0.000000,
          "stddev" : 0.000000,
          "percentile" : {
            "1.000000" : 0,
            "5.000000" : 0,
            "10.000000" : 0,
            "20.000000" : 0,
            "30.000000" : 0,
            "40.000000" : 0,
            "50.000000" : 0,
            "60.000000" : 0,
            "70.000000" : 0,
            "80.000000" : 0,
            "90.000000" : 0,
            "95.000000" : 0,
            "99.000000" : 0,
            "99.500000" : 0,
            "99.900000" : 0,
            "99.950000" : 0,
            "99.990000" : 0
          },
          "bins" : {

          }
        },
        "total_ios" : 0
      },
      "job_runtime" : 60076,
      "usr_cpu" : 1.929223,
      "sys_cpu" : 24.167721,
      "ctx" : 29876,
      "majf" : 0,
      "minf" : 23,
      "iodepth_level" : {
        "1" : 0.100000,
        "2" : 0.100000,
        "4" : 0.100000,
        "8" : 0.100000,
        "16" : 0.100000,
        "32" : 99.876114,
        ">=64" : 0.000000
      },
      "latency_ns" : {
        "2" : 0.000000,
        "4" : 0.000000,
        "10" : 0.000000,
        "20" : 0.000000,
        "50" : 0.000000,
        "100" : 0.000000,
        "250" : 0.000000,
        "500" : 0.000000,
        "750" : 0.000000,
        "1000" : 0.000000
      },
      "latency_us" : {
        "2" : 0.000000,
        "4" : 0.000000,
        "10" : 0.000000,
        "20" : 0.000000,
        "50" : 0.000000,
        "100" : 0.000000,
        "250" : 0.000000,
        "500" : 0.000000,
        "750" : 0.000000,
        "1000" : 0.000000
      },
      "latency_ms" : {
        "2" : 0.000000,
        "4" : 0.000000,
        "10" : 0.000000,
        "20" : 0.039963,
        "50" : 0.075930,
        "100" : 99.776206,
        "250" : 0.107901,
        "500" : 0.000000,
        "750" : 0.000000,
        "1000" : 0.000000,
        "2000" : 0.000000,
        ">=2000" : 0.000000
      },
      "latency_depth" : 32,
      "latency_target" : 0,
      "latency_percentile" : 100.000000,
      "latency_window" : 0
    }
  ],
  "disk_util" : [
    {
      "name" : "sda",
      "read_ios" : 50087,
      "write_ios" : 0,
      "read_merges" : 0,
      "write_merges" : 0,
      "read_ticks" : 3765366,
      "write_ticks" : 0,
      "in_queue" : 3765414,
      "util" : 99.832184
    }
  ]
}
