{
  "fio version" : "fio-3.8",
  "timestamp" : 1534652403,
  "timestamp_ms" : 1534652403367,
  "time" : "Sun Aug 19 04:20:03 2018",
  "jobs" : [
    {
      "jobname" : "wdpc",
      "groupid" : 0,
      "error" : 0,
      "eta" : 0,
      "elapsed" : 61,
      "job options" : {
        "ioengine" : "libaio",
        "group_reporting" : "1",
        "direct" : "1",
        "rw" : "randrw",
        "bs" : "4KB",
        "numjobs" : "2",
        "iodepth" : "16",
        "size" : "75%",
        "name" : "wdpc",
        "random_distribution" : "random",
        "random_generator" : "tausworthe",
        "allrandrepeat" : "1",
        "randseed" : "101",
        "rwmixread" : "5",
        "time_based" : "1",
        "runtime" : "60s",
        "filename" : "/dev/sda"
      },
      "read" : {
        "io_bytes" : 247648256,
        "io_kbytes" : 241844,
        "bw_bytes" : 4127333,
        "bw" : 4030,
        "iops" : 1007.649745,
        "runtime" : 60002,
        "total_ios" : 60461,
        "short_ios" : 0,
        "drop_ios" : 0,
        "slat_ns" : {
          "min" : 6709,
          "max" : 1460084,
          "mean" : 43353.423513,
          "stddev" : 39050.165177
        },
        "clat_ns" : {
          "min" : 199208,
          "max" : 49524125,
          "mean" : 1748088.852682,
          "stddev" : 1007962.135603,
          "percentile" : {
            "1.000000" : 428032,
            "5.000000" : 708608,
            "10.000000" : 856064,
            "20.000000" : 1056768,
            "30.000000" : 1204224,
            "40.000000" : 1335296,
            "50.000000" : 1531904,
            "60.000000" : 1777664,
            "70.000000" : 1990656,
            "80.000000" : 2310144,
            "90.000000" : 2768896,
            "95.000000" : 3260416,
            "99.000000" : 5603328,
            "99.500000" : 6651904,
            "99.900000" : 9633792,
            "99.950000" : 10682368,
            "99.990000" : 15663104
          },
          "bins" : {
            "199680" : 1,
            "209920" : 1,
            "218112" : 1,
            "222208" : 1,
            "224256" : 2,
            "226304" : 1,
            "228352" : 1,
            "230400" : 2,
            "234496" : 2,
            "236544" : 1,
            "238592" : 1,
            "240640" : 1,
            "242688" : 3,
            "244736" : 5,
            "246784" : 6,
            "248832" : 8,
            "250880" : 5,
            "252928" : 5,
            "254976" : 5,
            "257024" : 5,
            "259072" : 4,
            "261120" : 6,
            "264192" : 10,
            "268288" : 10,
            "272384" : 12,
            "276480" : 9,
            "280576" : 13,
            "284672" : 12,
            "288768" : 10,
            "292864" : 13,
            "296960" : 9,
            "301056" : 13,
            "305152" : 9,
            "309248" : 7,
            "313344" : 11,
            "317440" : 11,
            "321536" : 13,
            "325632" : 15,
            "329728" : 15,
            "333824" : 12,
            "337920" : 11,
            "342016" : 15,
            "346112" : 19,
            "350208" : 12,
            "354304" : 10,
            "358400" : 9,
            "362496" : 9,
            "366592" : 8,
            "370688" : 18,
            "374784" : 15,
            "378880" : 12,
            "382976" : 20,
            "387072" : 24,
            "391168" : 15,
            "395264" : 9,
            "399360" : 17,
            "403456" : 21,
            "407552" : 19,
            "411648" : 19,
            "415744" : 13,
            "419840" : 12,
            "423936" : 21,
            "428032" : 14,
            "432128" : 13,
            "436224" : 26,
            "440320" : 20,
            "444416" : 24,
            "448512" : 20,
            "452608" : 18,
            "456704" : 21,
            "460800" : 20,
            "464896" : 26,
            "468992" : 16,
            "473088" : 17,
            "477184" : 20,
            "481280" : 19,
            "485376" : 19,
            "489472" : 13,
            "493568" : 17,
            "497664" : 21,
            "501760" : 27,
            "505856" : 31,
            "509952" : 18,
            "514048" : 17,
            "518144" : 25,
            "522240" : 33,
            "528384" : 45,
            "536576" : 55,
            "544768" : 48,
            "552960" : 56,
            "561152" : 50,
            "569344" : 57,
            "577536" : 51,
            "585728" : 60,
            "593920" : 63,
            "602112" : 77,
            "610304" : 71,
            "618496" : 67,
            "626688" : 82,
            "634880" : 76,
            "643072" : 85,
            "651264" : 104,
            "659456" : 101,
            "667648" : 124,
            "675840" : 125,
            "684032" : 139,
            "692224" : 132,
            "700416" : 153,
            "708608" : 148,
            "716800" : 142,
            "724992" : 163,
            "733184" : 168,
            "741376" : 185,
            "749568" : 199,
            "757760" : 171,
            "765952" : 167,
            "774144" : 149,
            "782336" : 188,
            "790528" : 169,
            "798720" : 181,
            "806912" : 168,
            "815104" : 175,
            "823296" : 176,
            "831488" : 154,
            "839680" : 153,
            "847872" : 188,
            "856064" : 200,
            "864256" : 163,
            "872448" : 180,
            "880640" : 190,
            "888832" : 188,
            "897024" : 192,
            "905216" : 208,
            "913408" : 207,
            "921600" : 200,
            "929792" : 226,
            "937984" : 231,
            "946176" : 207,
            "954368" : 238,
            "962560" : 238,
            "970752" : 268,
            "978944" : 245,
            "987136" : 227,
            "995328" : 247,
            "1003520" : 265,
            "1011712" : 247,
            "1019904" : 299,
            "1028096" : 280,
            "1036288" : 327,
            "1044480" : 308,
            "1056768" : 569,
            "1073152" : 607,
            "1089536" : 641,
            "1105920" : 663,
            "1122304" : 685,
            "1138688" : 719,
            "1155072" : 766,
            "1171456" : 790,
            "1187840" : 821,
            "1204224" : 800,
            "1220608" : 838,
            "1236992" : 780,
            "1253376" : 757,
            "1269760" : 698,
            "1286144" : 686,
            "1302528" : 729,
            "1318912" : 640,
            "1335296" : 652,
            "1351680" : 596,
            "1368064" : 588,
            "1384448" : 600,
            "1400832" : 542,
            "1417216" : 537,
            "1433600" : 468,
            "1449984" : 449,
            "1466368" : 427,
            "1482752" : 442,
            "1499136" : 457,
            "1515520" : 432,
            "1531904" : 412,
            "1548288" : 407,
            "1564672" : 418,
            "1581056" : 393,
            "1597440" : 424,
            "1613824" : 424,
            "1630208" : 429,
            "1646592" : 402,
            "1662976" : 412,
            "1679360" : 428,
            "1695744" : 443,
            "1712128" : 417,
            "1728512" : 413,
            "1744896" : 461,
            "1761280" : 457,
            "1777664" : 492,
            "1794048" : 520,
            "1810432" : 509,
            "1826816" : 491,
            "1843200" : 518,
            "1859584" : 470,
            "1875968" : 438,
            "1892352" : 436,
            "1908736" : 451,
            "1925120" : 401,
            "1941504" : 395,
            "1957888" : 405,
            "1974272" : 393,
            "1990656" : 366,
            "2007040" : 382,
            "2023424" : 330,
            "2039808" : 331,
            "2056192" : 319,
            "2072576" : 320,
            "2088960" : 294,
            "2113536" : 623,
            "2146304" : 577,
            "2179072" : 582,
            "2211840" : 569,
            "2244608" : 593,
            "2277376" : 569,
            "2310144" : 561,
            "2342912" : 562,
            "2375680" : 516,
            "2408448" : 560,
            "2441216" : 495,
            "2473984" : 484,
            "2506752" : 461,
            "2539520" : 459,
            "2572288" : 392,
            "2605056" : 408,
            "2637824" : 378,
            "2670592" : 374,
            "2703360" : 327,
            "2736128" : 302,
            "2768896" : 294,
            "2801664" : 254,
            "2834432" : 249,
            "2867200" : 233,
            "2899968" : 227,
            "2932736" : 232,
            "2965504" : 197,
            "2998272" : 216,
            "3031040" : 175,
            "3063808" : 159,
            "3096576" : 152,
            "3129344" : 158,
            "3162112" : 173,
            "3194880" : 138,
            "3227648" : 153,
            "3260416" : 141,
            "3293184" : 124,
            "3325952" : 99,
            "3358720" : 109,
            "3391488" : 85,
            "3424256" : 100,
            "3457024" : 89,
            "3489792" : 82,
            "3522560" : 70,
            "3555328" : 61,
            "3588096" : 73,
            "3620864" : 70,
            "3653632" : 61,
            "3686400" : 54,
            "3719168" : 67,
            "3751936" : 56,
            "3784704" : 53,
            "3817472" : 48,
            "3850240" : 46,
            "3883008" : 34,
            "3915776" : 40,
            "3948544" : 42,
            "3981312" : 35,
            "4014080" : 31,
            "4046848" : 36,
            "4079616" : 34,
            "4112384" : 22,
            "4145152" : 26,
            "4177920" : 26,
            "4227072" : 50,
            "4292608" : 39,
            "4358144" : 62,
            "4423680" : 35,
            "4489216" : 31,
            "4554752" : 34,
            "4620288" : 36,
            "4685824" : 43,
            "4751360" : 36,
            "4816896" : 27,
            "4882432" : 40,
            "4947968" : 28,
            "5013504" : 22,
            "5079040" : 29,
            "5144576" : 26,
            "5210112" : 23,
            "5275648" : 38,
            "5341184" : 25,
            "5406720" : 28,
            "5472256" : 22,
            "5537792" : 25,
            "5603328" : 23,
            "5668864" : 29,
            "5734400" : 20,
            "5799936" : 29,
            "5865472" : 24,
            "5931008" : 22,
            "5996544" : 24,
            "6062080" : 23,
            "6127616" : 27,
            "6193152" : 11,
            "6258688" : 19,
            "6324224" : 17,
            "6389760" : 15,
            "6455296" : 7,
            "6520832" : 10,
            "6586368" : 15,
            "6651904" : 10,
            "6717440" : 13,
            "6782976" : 10,
            "6848512" : 13,
            "6914048" : 11,
            "6979584" : 8,
            "7045120" : 8,
            "7110656" : 12,
            "7176192" : 10,
            "7241728" : 6,
            "7307264" : 11,
            "7372800" : 4,
            "7438336" : 7,
            "7503872" : 5,
            "7569408" : 6,
            "7634944" : 10,
            "7700480" : 4,
            "7766016" : 6,
            "7831552" : 3,
            "7897088" : 5,
            "7962624" : 5,
            "8028160" : 5,
            "8093696" : 5,
            "8159232" : 5,
            "8224768" : 6,
            "8290304" : 6,
            "8355840" : 2,
            "8454144" : 10,
            "8585216" : 5,
            "8716288" : 7,
            "8847360" : 8,
            "8978432" : 11,
            "9109504" : 5,
            "9240576" : 2,
            "9371648" : 1,
            "9502720" : 5,
            "9633792" : 5,
            "9764864" : 4,
            "9895936" : 7,
            "10027008" : 2,
            "10158080" : 3,
            "10289152" : 4,
            "10420224" : 2,
            "10551296" : 2,
            "10682368" : 2,
            "10813440" : 3,
            "10944512" : 2,
            "11075584" : 1,
            "11206656" : 2,
            "11337728" : 1,
            "11468800" : 2,
            "11599872" : 3,
            "11862016" : 1,
            "11993088" : 1,
            "12255232" : 1,
            "12648448" : 1,
            "13041664" : 1,
            "13172736" : 2,
            "13565952" : 1,
            "14090240" : 1,
            "15663104" : 1,
            "16449536" : 1,
            "17432576" : 1,
            "18219008" : 1,
            "23986176" : 1,
            "35913728" : 1,
            "49545216" : 1
          }
        },
        "lat_ns" : {
          "min" : 259584,
          "max" : 49543083,
          "mean" : 1793780.872347,
          "stddev" : 1012771.304414
        },
        "bw_min" : 144,
        "bw_max" : 3584,
        "bw_agg" : 49.996071,
        "bw_mean" : 2014.841667,
        "bw_dev" : 559.036477,
        "bw_samples" : 240,
        "iops_min" : 36,
        "iops_max" : 896,
        "iops_mean" : 503.670833,
        "iops_stddev" : 139.765150,
        "iops_samples" : 240
      },
      "write" : {
        "io_bytes" : 4699389952,
        "io_kbytes" : 4589248,
        "bw_bytes" : 78320555,
        "bw" : 76484,
        "iops" : 19121.229292,
        "runtime" : 60002,
        "total_ios" : 1147312,
        "short_ios" : 0,
        "drop_ios" : 0,
        "slat_ns" : {
          "min" : 6125,
          "max" : 11298000,
          "mean" : 42509.250397,
          "stddev" : 47603.126300
        },
        "clat_ns" : {
          "min" : 275333,
          "max" : 56434875,
          "mean" : 1526945.130436,
          "stddev" : 1263744.325747,
          "percentile" : {
            "1.000000" : 561152,
            "5.000000" : 724992,
            "10.000000" : 872448,
            "20.000000" : 987136,
            "30.000000" : 1044480,
            "40.000000" : 1105920,
            "50.000000" : 1187840,
            "60.000000" : 1368064,
            "70.000000" : 1597440,
            "80.000000" : 1859584,
            "90.000000" : 2473984,
            "95.000000" : 2965504,
            "99.000000" : 5472256,
            "99.500000" : 6848512,
            "99.900000" : 13959168,
            "99.950000" : 23199744,
            "99.990000" : 44826624
          },
          "bins" : {
            "276480" : 1,
            "288768" : 1,
            "321536" : 1,
            "325632" : 2,
            "333824" : 2,
            "337920" : 1,
            "342016" : 1,
            "350208" : 2,
            "358400" : 2,
            "362496" : 1,
            "366592" : 1,
            "374784" : 1,
            "378880" : 5,
            "382976" : 2,
            "387072" : 6,
            "391168" : 3,
            "395264" : 3,
            "399360" : 2,
            "403456" : 4,
            "407552" : 4,
            "411648" : 12,
            "415744" : 13,
            "419840" : 10,
            "423936" : 24,
            "428032" : 16,
            "432128" : 13,
            "436224" : 22,
            "440320" : 19,
            "444416" : 27,
            "448512" : 46,
            "452608" : 49,
            "456704" : 63,
            "460800" : 60,
            "464896" : 73,
            "468992" : 55,
            "473088" : 61,
            "477184" : 91,
            "481280" : 106,
            "485376" : 129,
            "489472" : 179,
            "493568" : 253,
            "497664" : 259,
            "501760" : 264,
            "505856" : 250,
            "509952" : 275,
            "514048" : 367,
            "518144" : 423,
            "522240" : 489,
            "528384" : 1316,
            "536576" : 1525,
            "544768" : 1685,
            "552960" : 1783,
            "561152" : 2177,
            "569344" : 2660,
            "577536" : 2807,
            "585728" : 3028,
            "593920" : 2923,
            "602112" : 2809,
            "610304" : 2555,
            "618496" : 2480,
            "626688" : 2314,
            "634880" : 2104,
            "643072" : 1916,
            "651264" : 1863,
            "659456" : 2053,
            "667648" : 1993,
            "675840" : 1963,
            "684032" : 1927,
            "692224" : 2050,
            "700416" : 1987,
            "708608" : 2123,
            "716800" : 2204,
            "724992" : 2166,
            "733184" : 2218,
            "741376" : 2428,
            "749568" : 2540,
            "757760" : 2614,
            "765952" : 2717,
            "774144" : 2795,
            "782336" : 2835,
            "790528" : 2907,
            "798720" : 2947,
            "806912" : 2906,
            "815104" : 2968,
            "823296" : 3091,
            "831488" : 3297,
            "839680" : 3472,
            "847872" : 3794,
            "856064" : 3874,
            "864256" : 4365,
            "872448" : 4879,
            "880640" : 5403,
            "888832" : 5998,
            "897024" : 6702,
            "905216" : 7243,
            "913408" : 7698,
            "921600" : 8339,
            "929792" : 8540,
            "937984" : 9241,
            "946176" : 10184,
            "954368" : 10284,
            "962560" : 10739,
            "970752" : 11772,
            "978944" : 12446,
            "987136" : 13422,
            "995328" : 14438,
            "1003520" : 14892,
            "1011712" : 15522,
            "1019904" : 16113,
            "1028096" : 16573,
            "1036288" : 17849,
            "1044480" : 17057,
            "1056768" : 34274,
            "1073152" : 32821,
            "1089536" : 30632,
            "1105920" : 27786,
            "1122304" : 24764,
            "1138688" : 22115,
            "1155072" : 18688,
            "1171456" : 16152,
            "1187840" : 14371,
            "1204224" : 12807,
            "1220608" : 12306,
            "1236992" : 11145,
            "1253376" : 10721,
            "1269760" : 10102,
            "1286144" : 10244,
            "1302528" : 10448,
            "1318912" : 10570,
            "1335296" : 10383,
            "1351680" : 10075,
            "1368064" : 9806,
            "1384448" : 9729,
            "1400832" : 9475,
            "1417216" : 9242,
            "1433600" : 8487,
            "1449984" : 8319,
            "1466368" : 8031,
            "1482752" : 7553,
            "1499136" : 7527,
            "1515520" : 7454,
            "1531904" : 7412,
            "1548288" : 7227,
            "1564672" : 7145,
            "1581056" : 7309,
            "1597440" : 7708,
            "1613824" : 7551,
            "1630208" : 7678,
            "1646592" : 7740,
            "1662976" : 7981,
            "1679360" : 8101,
            "1695744" : 8496,
            "1712128" : 8121,
            "1728512" : 8019,
            "1744896" : 7550,
            "1761280" : 6748,
            "1777664" : 6598,
            "1794048" : 6248,
            "1810432" : 5825,
            "1826816" : 5527,
            "1843200" : 5172,
            "1859584" : 4968,
            "1875968" : 4574,
            "1892352" : 4255,
            "1908736" : 3955,
            "1925120" : 3808,
            "1941504" : 3579,
            "1957888" : 3432,
            "1974272" : 3215,
            "1990656" : 3065,
            "2007040" : 3008,
            "2023424" : 2974,
            "2039808" : 3015,
            "2056192" : 2881,
            "2072576" : 2967,
            "2088960" : 2792,
            "2113536" : 5443,
            "2146304" : 5558,
            "2179072" : 5613,
            "2211840" : 5780,
            "2244608" : 5766,
            "2277376" : 6037,
            "2310144" : 6008,
            "2342912" : 6214,
            "2375680" : 6244,
            "2408448" : 5990,
            "2441216" : 5984,
            "2473984" : 5721,
            "2506752" : 5231,
            "2539520" : 4946,
            "2572288" : 4744,
            "2605056" : 4327,
            "2637824" : 4185,
            "2670592" : 3803,
            "2703360" : 3544,
            "2736128" : 3345,
            "2768896" : 3245,
            "2801664" : 3074,
            "2834432" : 2922,
            "2867200" : 2653,
            "2899968" : 2484,
            "2932736" : 2179,
            "2965504" : 2049,
            "2998272" : 1826,
            "3031040" : 1679,
            "3063808" : 1483,
            "3096576" : 1419,
            "3129344" : 1244,
            "3162112" : 1394,
            "3194880" : 1249,
            "3227648" : 1180,
            "3260416" : 1093,
            "3293184" : 1048,
            "3325952" : 934,
            "3358720" : 864,
            "3391488" : 864,
            "3424256" : 832,
            "3457024" : 775,
            "3489792" : 794,
            "3522560" : 656,
            "3555328" : 735,
            "3588096" : 755,
            "3620864" : 676,
            "3653632" : 639,
            "3686400" : 589,
            "3719168" : 628,
            "3751936" : 612,
            "3784704" : 647,
            "3817472" : 612,
            "3850240" : 567,
            "3883008" : 539,
            "3915776" : 550,
            "3948544" : 515,
            "3981312" : 483,
            "4014080" : 546,
            "4046848" : 510,
            "4079616" : 511,
            "4112384" : 505,
            "4145152" : 532,
            "4177920" : 472,
            "4227072" : 1049,
            "4292608" : 994,
            "4358144" : 945,
            "4423680" : 894,
            "4489216" : 842,
            "4554752" : 757,
            "4620288" : 634,
            "4685824" : 622,
            "4751360" : 630,
            "4816896" : 602,
            "4882432" : 630,
            "4947968" : 625,
            "5013504" : 703,
            "5079040" : 699,
            "5144576" : 718,
            "5210112" : 632,
            "5275648" : 561,
            "5341184" : 533,
            "5406720" : 546,
            "5472256" : 455,
            "5537792" : 391,
            "5603328" : 390,
            "5668864" : 372,
            "5734400" : 372,
            "5799936" : 325,
            "5865472" : 265,
            "5931008" : 284,
            "5996544" : 285,
            "6062080" : 247,
            "6127616" : 219,
            "6193152" : 239,
            "6258688" : 242,
            "6324224" : 284,
            "6389760" : 190,
            "6455296" : 231,
            "6520832" : 245,
            "6586368" : 236,
            "6651904" : 214,
            "6717440" : 220,
            "6782976" : 179,
            "6848512" : 187,
            "6914048" : 134,
            "6979584" : 178,
            "7045120" : 184,
            "7110656" : 164,
            "7176192" : 192,
            "7241728" : 107,
            "7307264" : 95,
            "7372800" : 104,
            "7438336" : 125,
            "7503872" : 168,
            "7569408" : 143,
            "7634944" : 154,
            "7700480" : 98,
            "7766016" : 102,
            "7831552" : 108,
            "7897088" : 85,
            "7962624" : 85,
            "8028160" : 98,
            "8093696" : 95,
            "8159232" : 78,
            "8224768" : 75,
            "8290304" : 77,
            "8355840" : 56,
            "8454144" : 133,
            "8585216" : 164,
            "8716288" : 173,
            "8847360" : 120,
            "8978432" : 96,
            "9109504" : 92,
            "9240576" : 66,
            "9371648" : 96,
            "9502720" : 92,
            "9633792" : 37,
            "9764864" : 45,
            "9895936" : 53,
            "10027008" : 44,
            "10158080" : 32,
            "10289152" : 46,
            "10420224" : 58,
            "10551296" : 73,
            "10682368" : 42,
            "10813440" : 22,
            "10944512" : 13,
            "11075584" : 28,
            "11206656" : 30,
            "11337728" : 10,
            "11468800" : 10,
            "11599872" : 5,
            "11730944" : 10,
            "11862016" : 28,
            "11993088" : 19,
            "12124160" : 3,
            "12255232" : 6,
            "12386304" : 12,
            "12517376" : 8,
            "12648448" : 5,
            "12779520" : 3,
            "12910592" : 5,
            "13041664" : 14,
            "13172736" : 10,
            "13303808" : 20,
            "13434880" : 17,
            "13565952" : 4,
            "13697024" : 47,
            "13828096" : 27,
            "13959168" : 31,
            "14090240" : 39,
            "14221312" : 28,
            "14352384" : 25,
            "14483456" : 24,
            "14614528" : 33,
            "14745600" : 22,
            "14876672" : 6,
            "15007744" : 5,
            "15138816" : 20,
            "15269888" : 59,
            "15400960" : 31,
            "15532032" : 2,
            "15663104" : 14,
            "15794176" : 8,
            "15925248" : 14,
            "16056320" : 8,
            "16187392" : 2,
            "16318464" : 3,
            "16449536" : 3,
            "16580608" : 10,
            "16711680" : 6,
            "16908288" : 28,
            "17170432" : 28,
            "17432576" : 22,
            "17694720" : 14,
            "17956864" : 1,
            "18219008" : 19,
            "18481152" : 8,
            "18743296" : 3,
            "19005440" : 26,
            "19267584" : 14,
            "19529728" : 3,
            "20840448" : 6,
            "21102592" : 7,
            "21364736" : 30,
            "22675456" : 2,
            "23199744" : 1,
            "24248320" : 1,
            "25034752" : 1,
            "26345472" : 4,
            "26607616" : 4,
            "26869760" : 8,
            "27131904" : 5,
            "27394048" : 18,
            "27656192" : 48,
            "27918336" : 7,
            "28180480" : 6,
            "28442624" : 10,
            "28704768" : 11,
            "28966912" : 10,
            "29229056" : 8,
            "29491200" : 2,
            "30539776" : 10,
            "30801920" : 11,
            "31064064" : 1,
            "31850496" : 8,
            "32112640" : 1,
            "32899072" : 1,
            "33161216" : 14,
            "33423360" : 4,
            "33816576" : 65,
            "34340864" : 14,
            "34865152" : 1,
            "35389440" : 25,
            "35913728" : 3,
            "36438016" : 28,
            "36962304" : 13,
            "37486592" : 17,
            "38010880" : 3,
            "38535168" : 4,
            "39059456" : 1,
            "39583744" : 3,
            "40108032" : 3,
            "40632320" : 4,
            "41156608" : 1,
            "41680896" : 22,
            "42205184" : 18,
            "42729472" : 9,
            "43778048" : 1,
            "44302336" : 6,
            "44826624" : 25,
            "45350912" : 4,
            "45875200" : 17,
            "46399488" : 20,
            "46923776" : 11,
            "47448064" : 4,
            "47972352" : 7,
            "48496640" : 4,
            "49020928" : 10,
            "50069504" : 1,
            "50593792" : 2,
            "51118080" : 21,
            "51642368" : 1,
            "52690944" : 2,
            "53215232" : 3,
            "53739520" : 5,
            "55312384" : 1,
            "56360960" : 1
          }
        },
        "lat_ns" : {
          "min" : 330166,
          "max" : 56472208,
          "mean" : 1571567.895616,
          "stddev" : 1267509.944618
        },
        "bw_min" : 2528,
        "bw_max" : 61024,
        "bw_agg" : 49.990216,
        "bw_mean" : 38234.516667,
        "bw_dev" : 10195.470124,
        "bw_samples" : 240,
        "iops_min" : 632,
        "iops_max" : 15256,
        "iops_mean" : 9558.587500,
        "iops_stddev" : 2548.881351,
        "iops_samples" : 240
      },
      "trim" : {
        "io_bytes" : 0,
        "io_kbytes" : 0,
        "bw_bytes" : 0,
        "bw" : 0,
        "iops" : 0.000000,
        "runtime" : 0,
        "total_ios" : 0,
        "short_ios" : 0,
        "drop_ios" : 0,
        "slat_ns" : {
          "min" : 0,
          "max" : 0,
          "mean" : 0.000000,
          "stddev" : 0.000000
        },
        "clat_ns" : {
          "min" : 0,
          "max" : 0,
          "mean" : 0.000000,
          "stddev" : 0.000000,
          "percentile" : {
            "1.000000" : 0,
            "5.000000" : 0,
            "10.000000" : 0,
            "20.000000" : 0,
            "30.000000" : 0,
            "40.000000" : 0,
            "50.000000" : 0,
            "60.000000" : 0,
            "70.000000" : 0,
            "80.000000" : 0,
            "90.000000" : 0,
            "95.000000" : 0,
            "99.000000" : 0,
            "99.500000" : 0,
            "99.900000" : 0,
            "99.950000" : 0,
            "99.990000" : 0
          },
          "bins" : {

          }
        },
        "lat_ns" : {
          "min" : 0,
          "max" : 0,
          "mean" : 0.000000,
          "stddev" : 0.000000
        },
        "bw_min" : 0,
        "bw_max" : 0,
        "bw_agg" : 0.000000,
        "bw_mean" : 0.000000,
        "bw_dev" : 0.000000,
        "bw_samples" : 0,
        "iops_min" : 0,
        "iops_max" : 0,
        "iops_mean" : 0.000000,
        "iops_stddev" : 0.000000,
        "iops_samples" : 0
      },
      "sync" : {
        "lat_ns" : {
          "min" : 0,
          "max" : 0,
          "mean" : 0.000000,
          "stddev" : 0.000000,
          "percentile" : {
            "1.000000" : 0,
            "5.000000" : 0,
            "10.000000" : 0,
            "20.000000" : 0,
            "30.000000" : 0,
            "40.000000" : 0,
            "50.000000" : 0,
            "60.000000" : 0,
            "70.000000" : 0,
            "80.000000" : 0,
            "90.000000" : 0,
            "95.000000" : 0,
            "99.000000" : 0,
            "99.500000" : 0,
            "99.900000" : 0,
            "99.950000" : 0,
            "99.990000" : 0
          },
          "bins" : {

          }
        },
        "total_ios" : 0
      },
      "job_runtime" : 120001,
      "usr_cpu" : 9.695753,
      "sys_cpu" : 49.692086,
      "ctx" : 295434,
      "majf" : 0,
      "minf" : 50,
      "iodepth_level" : {
        "1" : 0.100000,
        "2" : 0.100000,
        "4" : 0.100000,
        "8" : 0.100000,
        "16" : 99.997516,
        "32" : 0.000000,
        ">=64" : 0.000000
      },
      "latency_ns" : {
        "2" : 0.000000,
        "4" : 0.000000,
        "10" : 0.000000,
        "20" : 0.000000,
        "50" : 0.000000,
        "100" : 0.000000,
        "250" : 0.000000,
        "500" : 0.000000,
        "750" : 0.000000,
        "1000" : 0.000000
      },
      "latency_us" : {
        "2" : 0.000000,
        "4" : 0.000000,
        "10" : 0.000000,
        "20" : 0.000000,
        "50" : 0.000000,
        "100" : 0.000000,
        "250" : 0.010000,
        "500" : 0.211712,
        "750" : 5.416167,
        "1000" : 16.569090
      },
      "latency_ms" : {
        "2" : 60.020716,
        "4" : 15.300888,
        "10" : 2.324112,
        "20" : 0.102668,
        "50" : 0.048436,
        "100" : 0.010000,
        "250" : 0.000000,
        "500" : 0.000000,
        "750" : 0.000000,
        "1000" : 0.000000,
        "2000" : 0.000000,
        ">=2000" : 0.000000
      },
      "latency_depth" : 16,
      "latency_target" : 0,
      "latency_percentile" : 100.000000,
      "latency_window" : 0
    }
  ],
  "disk_util" : [
    {
      "name" : "sda",
      "read_ios" : 60441,
      "write_ios" : 1145978,
      "read_merges" : 0,
      "write_merges" : 0,
      "read_ticks" : 96493,
      "write_ticks" : 1566240,
      "in_queue" : 1664329,
      "util" : 99.961621
    }
  ]
}
