{
  "fio version" : "fio-3.8",
  "timestamp" : 1540751876,
  "timestamp_ms" : 1540751876769,
  "time" : "Sun Oct 28 13:37:56 2018",
  "jobs" : [
    {
      "jobname" : "wdpc",
      "groupid" : 0,
      "error" : 0,
      "eta" : 0,
      "elapsed" : 601,
      "job options" : {
        "ioengine" : "libaio",
        "group_reporting" : "1",
        "direct" : "1",
        "rw" : "randrw",
        "bssplit" : "12KB/53:8KB/20:4KB/10:128KB,512KB/72:4KB/14:508KB",
        "numjobs" : "2",
        "iodepth" : "16",
        "size" : "75%",
        "name" : "wdpc",
        "random_distribution" : "random",
        "random_generator" : "tausworthe",
        "allrandrepeat" : "1",
        "randseed" : "101",
        "rwmixread" : "87",
        "time_based" : "1",
        "runtime" : "600s",
        "filename" : "/dev/sdb"
      },
      "read" : {
        "io_bytes" : 64947052544,
        "io_kbytes" : 63424856,
        "bw_bytes" : 108242922,
        "bw" : 105705,
        "iops" : 3849.801337,
        "runtime" : 600012,
        "total_ios" : 2309927,
        "short_ios" : 0,
        "drop_ios" : 0,
        "slat_ns" : {
          "min" : 1727,
          "max" : 599603,
          "mean" : 13360.951080,
          "stddev" : 8882.448646
        },
        "clat_ns" : {
          "min" : 136308,
          "max" : 44684655,
          "mean" : 6210376.364186,
          "stddev" : 3999581.235946,
          "percentile" : {
            "1.000000" : 1056768,
            "5.000000" : 1679360,
            "10.000000" : 2113536,
            "20.000000" : 2834432,
            "30.000000" : 3522560,
            "40.000000" : 4292608,
            "50.000000" : 5210112,
            "60.000000" : 6258688,
            "70.000000" : 7569408,
            "80.000000" : 9240576,
            "90.000000" : 11730944,
            "95.000000" : 13959168,
            "99.000000" : 18743296,
            "99.500000" : 20840448,
            "99.900000" : 26345472,
            "99.950000" : 28966912,
            "99.990000" : 34865152
          },
          "bins" : {
            "136192" : 1,
            "138240" : 1,
            "140288" : 1,
            "142336" : 1,
            "148480" : 1,
            "156672" : 1,
            "158720" : 1,
            "164864" : 1,
            "166912" : 1,
            "168960" : 1,
            "171008" : 1,
            "173056" : 1,
            "175104" : 2,
            "181248" : 1,
            "183296" : 3,
            "185344" : 2,
            "187392" : 1,
            "189440" : 2,
            "191488" : 1,
            "193536" : 2,
            "195584" : 3,
            "197632" : 1,
            "199680" : 2,
            "201728" : 3,
            "203776" : 2,
            "205824" : 2,
            "207872" : 2,
            "209920" : 2,
            "211968" : 2,
            "214016" : 4,
            "216064" : 3,
            "218112" : 3,
            "220160" : 5,
            "222208" : 6,
            "224256" : 1,
            "226304" : 5,
            "228352" : 4,
            "230400" : 3,
            "232448" : 2,
            "234496" : 3,
            "236544" : 5,
            "238592" : 4,
            "240640" : 2,
            "242688" : 3,
            "244736" : 2,
            "246784" : 1,
            "248832" : 3,
            "250880" : 2,
            "252928" : 2,
            "254976" : 5,
            "257024" : 4,
            "259072" : 2,
            "261120" : 5,
            "264192" : 10,
            "268288" : 11,
            "272384" : 10,
            "276480" : 11,
            "280576" : 13,
            "284672" : 4,
            "288768" : 16,
            "292864" : 8,
            "296960" : 10,
            "301056" : 25,
            "305152" : 11,
            "309248" : 26,
            "313344" : 15,
            "317440" : 19,
            "321536" : 12,
            "325632" : 20,
            "329728" : 26,
            "333824" : 19,
            "337920" : 18,
            "342016" : 17,
            "346112" : 10,
            "350208" : 17,
            "354304" : 19,
            "358400" : 18,
            "362496" : 19,
            "366592" : 21,
            "370688" : 21,
            "374784" : 27,
            "378880" : 20,
            "382976" : 26,
            "387072" : 21,
            "391168" : 28,
            "395264" : 33,
            "399360" : 28,
            "403456" : 35,
            "407552" : 25,
            "411648" : 26,
            "415744" : 33,
            "419840" : 27,
            "423936" : 21,
            "428032" : 25,
            "432128" : 32,
            "436224" : 40,
            "440320" : 26,
            "444416" : 37,
            "448512" : 43,
            "452608" : 42,
            "456704" : 34,
            "460800" : 44,
            "464896" : 36,
            "468992" : 41,
            "473088" : 34,
            "477184" : 41,
            "481280" : 36,
            "485376" : 45,
            "489472" : 49,
            "493568" : 57,
            "497664" : 40,
            "501760" : 60,
            "505856" : 44,
            "509952" : 58,
            "514048" : 51,
            "518144" : 51,
            "522240" : 54,
            "528384" : 103,
            "536576" : 114,
            "544768" : 95,
            "552960" : 116,
            "561152" : 130,
            "569344" : 128,
            "577536" : 122,
            "585728" : 128,
            "593920" : 147,
            "602112" : 145,
            "610304" : 154,
            "618496" : 166,
            "626688" : 174,
            "634880" : 175,
            "643072" : 197,
            "651264" : 182,
            "659456" : 193,
            "667648" : 177,
            "675840" : 238,
            "684032" : 213,
            "692224" : 222,
            "700416" : 226,
            "708608" : 239,
            "716800" : 252,
            "724992" : 236,
            "733184" : 247,
            "741376" : 275,
            "749568" : 273,
            "757760" : 262,
            "765952" : 306,
            "774144" : 294,
            "782336" : 292,
            "790528" : 310,
            "798720" : 282,
            "806912" : 339,
            "815104" : 332,
            "823296" : 368,
            "831488" : 390,
            "839680" : 361,
            "847872" : 347,
            "856064" : 405,
            "864256" : 370,
            "872448" : 394,
            "880640" : 417,
            "888832" : 402,
            "897024" : 433,
            "905216" : 450,
            "913408" : 467,
            "921600" : 478,
            "929792" : 473,
            "937984" : 490,
            "946176" : 521,
            "954368" : 503,
            "962560" : 533,
            "970752" : 519,
            "978944" : 491,
            "987136" : 558,
            "995328" : 631,
            "1003520" : 547,
            "1011712" : 579,
            "1019904" : 580,
            "1028096" : 615,
            "1036288" : 607,
            "1044480" : 668,
            "1056768" : 1296,
            "1073152" : 1447,
            "1089536" : 1459,
            "1105920" : 1514,
            "1122304" : 1502,
            "1138688" : 1570,
            "1155072" : 1643,
            "1171456" : 1695,
            "1187840" : 1717,
            "1204224" : 1847,
            "1220608" : 1836,
            "1236992" : 1895,
            "1253376" : 1969,
            "1269760" : 2056,
            "1286144" : 2035,
            "1302528" : 2142,
            "1318912" : 2180,
            "1335296" : 2337,
            "1351680" : 2321,
            "1368064" : 2395,
            "1384448" : 2389,
            "1400832" : 2549,
            "1417216" : 2541,
            "1433600" : 2645,
            "1449984" : 2728,
            "1466368" : 2924,
            "1482752" : 2829,
            "1499136" : 2883,
            "1515520" : 2945,
            "1531904" : 3111,
            "1548288" : 3060,
            "1564672" : 3010,
            "1581056" : 3149,
            "1597440" : 3302,
            "1613824" : 3425,
            "1630208" : 3399,
            "1646592" : 3432,
            "1662976" : 3438,
            "1679360" : 3632,
            "1695744" : 3702,
            "1712128" : 3823,
            "1728512" : 3809,
            "1744896" : 3917,
            "1761280" : 3916,
            "1777664" : 3946,
            "1794048" : 4049,
            "1810432" : 4077,
            "1826816" : 4127,
            "1843200" : 4221,
            "1859584" : 4231,
            "1875968" : 4218,
            "1892352" : 4291,
            "1908736" : 4331,
            "1925120" : 4595,
            "1941504" : 4445,
            "1957888" : 4615,
            "1974272" : 4646,
            "1990656" : 4670,
            "2007040" : 4652,
            "2023424" : 4751,
            "2039808" : 4810,
            "2056192" : 4983,
            "2072576" : 4909,
            "2088960" : 4940,
            "2113536" : 9875,
            "2146304" : 10103,
            "2179072" : 10178,
            "2211840" : 10388,
            "2244608" : 10296,
            "2277376" : 10565,
            "2310144" : 10505,
            "2342912" : 10455,
            "2375680" : 10731,
            "2408448" : 10714,
            "2441216" : 10759,
            "2473984" : 10848,
            "2506752" : 10726,
            "2539520" : 10884,
            "2572288" : 11007,
            "2605056" : 10931,
            "2637824" : 11050,
            "2670592" : 11140,
            "2703360" : 10781,
            "2736128" : 10953,
            "2768896" : 11250,
            "2801664" : 11109,
            "2834432" : 11043,
            "2867200" : 10985,
            "2899968" : 11044,
            "2932736" : 10982,
            "2965504" : 11064,
            "2998272" : 11031,
            "3031040" : 10881,
            "3063808" : 11181,
            "3096576" : 10728,
            "3129344" : 10727,
            "3162112" : 10889,
            "3194880" : 10765,
            "3227648" : 10670,
            "3260416" : 10681,
            "3293184" : 10791,
            "3325952" : 10599,
            "3358720" : 10527,
            "3391488" : 10453,
            "3424256" : 10469,
            "3457024" : 10413,
            "3489792" : 10409,
            "3522560" : 10322,
            "3555328" : 10242,
            "3588096" : 10095,
            "3620864" : 10184,
            "3653632" : 9948,
            "3686400" : 9922,
            "3719168" : 9868,
            "3751936" : 9886,
            "3784704" : 9848,
            "3817472" : 9795,
            "3850240" : 9909,
            "3883008" : 9576,
            "3915776" : 9602,
            "3948544" : 9632,
            "3981312" : 9475,
            "4014080" : 9346,
            "4046848" : 9451,
            "4079616" : 9259,
            "4112384" : 9192,
            "4145152" : 9065,
            "4177920" : 9080,
            "4227072" : 18382,
            "4292608" : 17816,
            "4358144" : 17947,
            "4423680" : 17527,
            "4489216" : 17205,
            "4554752" : 17232,
            "4620288" : 17271,
            "4685824" : 17100,
            "4751360" : 16706,
            "4816896" : 16567,
            "4882432" : 16821,
            "4947968" : 16474,
            "5013504" : 16319,
            "5079040" : 16197,
            "5144576" : 15993,
            "5210112" : 15835,
            "5275648" : 15550,
            "5341184" : 15459,
            "5406720" : 15243,
            "5472256" : 15008,
            "5537792" : 15153,
            "5603328" : 14607,
            "5668864" : 14536,
            "5734400" : 14257,
            "5799936" : 14327,
            "5865472" : 14221,
            "5931008" : 14110,
            "5996544" : 13705,
            "6062080" : 13564,
            "6127616" : 13461,
            "6193152" : 13144,
            "6258688" : 13071,
            "6324224" : 12908,
            "6389760" : 12760,
            "6455296" : 12664,
            "6520832" : 12469,
            "6586368" : 12009,
            "6651904" : 11907,
            "6717440" : 11981,
            "6782976" : 11595,
            "6848512" : 11717,
            "6914048" : 11300,
            "6979584" : 11176,
            "7045120" : 11101,
            "7110656" : 11084,
            "7176192" : 10832,
            "7241728" : 10896,
            "7307264" : 10709,
            "7372800" : 10560,
            "7438336" : 10598,
            "7503872" : 10060,
            "7569408" : 10267,
            "7634944" : 10281,
            "7700480" : 9879,
            "7766016" : 9784,
            "7831552" : 9945,
            "7897088" : 9710,
            "7962624" : 9806,
            "8028160" : 9484,
            "8093696" : 9416,
            "8159232" : 9246,
            "8224768" : 9449,
            "8290304" : 9225,
            "8355840" : 9027,
            "8454144" : 17751,
            "8585216" : 17660,
            "8716288" : 17229,
            "8847360" : 16874,
            "8978432" : 16532,
            "9109504" : 15755,
            "9240576" : 16046,
            "9371648" : 15412,
            "9502720" : 14777,
            "9633792" : 14634,
            "9764864" : 14246,
            "9895936" : 14027,
            "10027008" : 13664,
            "10158080" : 13234,
            "10289152" : 12982,
            "10420224" : 12296,
            "10551296" : 12306,
            "10682368" : 11821,
            "10813440" : 11474,
            "10944512" : 10975,
            "11075584" : 10539,
            "11206656" : 10597,
            "11337728" : 10260,
            "11468800" : 9677,
            "11599872" : 9547,
            "11730944" : 9374,
            "11862016" : 8867,
            "11993088" : 8587,
            "12124160" : 8212,
            "12255232" : 7852,
            "12386304" : 7419,
            "12517376" : 7423,
            "12648448" : 7054,
            "12779520" : 6825,
            "12910592" : 6602,
            "13041664" : 6317,
            "13172736" : 6083,
            "13303808" : 5808,
            "13434880" : 5741,
            "13565952" : 5355,
            "13697024" : 5226,
            "13828096" : 4942,
            "13959168" : 4904,
            "14090240" : 4652,
            "14221312" : 4416,
            "14352384" : 4476,
            "14483456" : 4280,
            "14614528" : 3977,
            "14745600" : 3797,
            "14876672" : 3558,
            "15007744" : 3453,
            "15138816" : 3316,
            "15269888" : 3107,
            "15400960" : 3095,
            "15532032" : 3003,
            "15663104" : 2799,
            "15794176" : 2731,
            "15925248" : 2587,
            "16056320" : 2444,
            "16187392" : 2338,
            "16318464" : 2182,
            "16449536" : 2137,
            "16580608" : 2031,
            "16711680" : 1988,
            "16908288" : 3798,
            "17170432" : 3441,
            "17432576" : 3014,
            "17694720" : 2864,
            "17956864" : 2608,
            "18219008" : 2415,
            "18481152" : 2174,
            "18743296" : 1962,
            "19005440" : 1839,
            "19267584" : 1668,
            "19529728" : 1557,
            "19791872" : 1452,
            "20054016" : 1316,
            "20316160" : 1166,
            "20578304" : 1148,
            "20840448" : 1022,
            "21102592" : 885,
            "21364736" : 897,
            "21626880" : 792,
            "21889024" : 740,
            "22151168" : 665,
            "22413312" : 630,
            "22675456" : 527,
            "22937600" : 484,
            "23199744" : 432,
            "23461888" : 379,
            "23724032" : 366,
            "23986176" : 348,
            "24248320" : 318,
            "24510464" : 268,
            "24772608" : 232,
            "25034752" : 261,
            "25296896" : 236,
            "25559040" : 208,
            "25821184" : 176,
            "26083328" : 186,
            "26345472" : 161,
            "26607616" : 174,
            "26869760" : 137,
            "27131904" : 140,
            "27394048" : 136,
            "27656192" : 90,
            "27918336" : 83,
            "28180480" : 94,
            "28442624" : 75,
            "28704768" : 69,
            "28966912" : 74,
            "29229056" : 89,
            "29491200" : 59,
            "29753344" : 49,
            "30015488" : 61,
            "30277632" : 49,
            "30539776" : 42,
            "30801920" : 44,
            "31064064" : 44,
            "31326208" : 54,
            "31588352" : 45,
            "31850496" : 42,
            "32112640" : 35,
            "32374784" : 28,
            "32636928" : 36,
            "32899072" : 37,
            "33161216" : 28,
            "33423360" : 37,
            "33816576" : 46,
            "34340864" : 37,
            "34865152" : 43,
            "35389440" : 31,
            "35913728" : 20,
            "36438016" : 21,
            "36962304" : 19,
            "37486592" : 16,
            "38010880" : 11,
            "38535168" : 11,
            "39059456" : 8,
            "39583744" : 8,
            "40108032" : 7,
            "40632320" : 15,
            "41156608" : 4,
            "41680896" : 7,
            "42205184" : 3,
            "43253760" : 4,
            "43778048" : 3,
            "44302336" : 1,
            "44826624" : 1
          }
        },
        "lat_ns" : {
          "min" : 142087,
          "max" : 44715172,
          "mean" : 6223988.561891,
          "stddev" : 3999765.514572
        },
        "bw_min" : 29824,
        "bw_max" : 73624,
        "bw_agg" : 49.996889,
        "bw_mean" : 52849.211667,
        "bw_dev" : 6909.041986,
        "bw_samples" : 2400,
        "iops_min" : 1150,
        "iops_max" : 2546,
        "iops_mean" : 1924.752917,
        "iops_stddev" : 244.296914,
        "iops_samples" : 2400
      },
      "write" : {
        "io_bytes" : 101424173056,
        "io_kbytes" : 99047044,
        "bw_bytes" : 169036907,
        "bw" : 165075,
        "iops" : 574.406845,
        "runtime" : 600012,
        "total_ios" : 344651,
        "short_ios" : 0,
        "drop_ios" : 0,
        "slat_ns" : {
          "min" : 2004,
          "max" : 684588,
          "mean" : 38122.865937,
          "stddev" : 22664.174092
        },
        "clat_ns" : {
          "min" : 221638,
          "max" : 55642853,
          "mean" : 13931336.363962,
          "stddev" : 5905021.147815,
          "percentile" : {
            "1.000000" : 4046848,
            "5.000000" : 6127616,
            "10.000000" : 7372800,
            "20.000000" : 8978432,
            "30.000000" : 10420224,
            "40.000000" : 11730944,
            "50.000000" : 13041664,
            "60.000000" : 14483456,
            "70.000000" : 16056320,
            "80.000000" : 18219008,
            "90.000000" : 21626880,
            "95.000000" : 25034752,
            "99.000000" : 31850496,
            "99.500000" : 34865152,
            "99.900000" : 42205184,
            "99.950000" : 44826624,
            "99.990000" : 50069504
          },
          "bins" : {
            "222208" : 1,
            "242688" : 1,
            "288768" : 1,
            "321536" : 1,
            "366592" : 1,
            "370688" : 1,
            "382976" : 1,
            "391168" : 1,
            "411648" : 1,
            "415744" : 1,
            "423936" : 2,
            "432128" : 1,
            "448512" : 2,
            "460800" : 1,
            "464896" : 1,
            "473088" : 2,
            "489472" : 1,
            "497664" : 1,
            "561152" : 1,
            "577536" : 1,
            "602112" : 1,
            "626688" : 3,
            "659456" : 1,
            "667648" : 1,
            "675840" : 1,
            "692224" : 1,
            "708608" : 1,
            "724992" : 2,
            "741376" : 1,
            "749568" : 1,
            "774144" : 1,
            "782336" : 1,
            "790528" : 1,
            "798720" : 2,
            "806912" : 2,
            "815104" : 5,
            "831488" : 1,
            "839680" : 2,
            "847872" : 3,
            "856064" : 2,
            "864256" : 4,
            "872448" : 2,
            "888832" : 1,
            "897024" : 2,
            "905216" : 2,
            "913408" : 2,
            "921600" : 2,
            "929792" : 4,
            "946176" : 2,
            "954368" : 1,
            "970752" : 3,
            "995328" : 2,
            "1011712" : 3,
            "1019904" : 1,
            "1028096" : 1,
            "1036288" : 3,
            "1056768" : 7,
            "1073152" : 6,
            "1089536" : 3,
            "1105920" : 1,
            "1122304" : 4,
            "1138688" : 1,
            "1155072" : 5,
            "1171456" : 2,
            "1187840" : 4,
            "1204224" : 2,
            "1220608" : 2,
            "1236992" : 4,
            "1253376" : 1,
            "1269760" : 3,
            "1286144" : 2,
            "1302528" : 2,
            "1318912" : 3,
            "1335296" : 2,
            "1351680" : 6,
            "1368064" : 6,
            "1384448" : 5,
            "1400832" : 3,
            "1417216" : 1,
            "1433600" : 6,
            "1466368" : 6,
            "1482752" : 1,
            "1499136" : 4,
            "1515520" : 4,
            "1531904" : 5,
            "1548288" : 5,
            "1564672" : 4,
            "1581056" : 3,
            "1597440" : 4,
            "1613824" : 11,
            "1630208" : 9,
            "1646592" : 5,
            "1662976" : 5,
            "1679360" : 9,
            "1695744" : 4,
            "1712128" : 6,
            "1728512" : 6,
            "1744896" : 7,
            "1761280" : 4,
            "1777664" : 9,
            "1794048" : 7,
            "1810432" : 6,
            "1826816" : 12,
            "1843200" : 6,
            "1859584" : 8,
            "1875968" : 8,
            "1892352" : 5,
            "1908736" : 7,
            "1925120" : 9,
            "1941504" : 8,
            "1957888" : 8,
            "1974272" : 6,
            "1990656" : 11,
            "2007040" : 8,
            "2023424" : 8,
            "2039808" : 9,
            "2056192" : 13,
            "2072576" : 9,
            "2088960" : 7,
            "2113536" : 21,
            "2146304" : 19,
            "2179072" : 26,
            "2211840" : 18,
            "2244608" : 24,
            "2277376" : 15,
            "2310144" : 18,
            "2342912" : 20,
            "2375680" : 33,
            "2408448" : 26,
            "2441216" : 29,
            "2473984" : 22,
            "2506752" : 18,
            "2539520" : 28,
            "2572288" : 36,
            "2605056" : 22,
            "2637824" : 41,
            "2670592" : 33,
            "2703360" : 32,
            "2736128" : 33,
            "2768896" : 27,
            "2801664" : 38,
            "2834432" : 45,
            "2867200" : 36,
            "2899968" : 46,
            "2932736" : 30,
            "2965504" : 41,
            "2998272" : 45,
            "3031040" : 51,
            "3063808" : 44,
            "3096576" : 41,
            "3129344" : 44,
            "3162112" : 56,
            "3194880" : 61,
            "3227648" : 65,
            "3260416" : 46,
            "3293184" : 53,
            "3325952" : 59,
            "3358720" : 59,
            "3391488" : 61,
            "3424256" : 48,
            "3457024" : 54,
            "3489792" : 66,
            "3522560" : 76,
            "3555328" : 59,
            "3588096" : 75,
            "3620864" : 77,
            "3653632" : 77,
            "3686400" : 60,
            "3719168" : 78,
            "3751936" : 77,
            "3784704" : 84,
            "3817472" : 100,
            "3850240" : 92,
            "3883008" : 88,
            "3915776" : 88,
            "3948544" : 107,
            "3981312" : 96,
            "4014080" : 96,
            "4046848" : 117,
            "4079616" : 107,
            "4112384" : 110,
            "4145152" : 122,
            "4177920" : 127,
            "4227072" : 237,
            "4292608" : 295,
            "4358144" : 291,
            "4423680" : 284,
            "4489216" : 289,
            "4554752" : 296,
            "4620288" : 295,
            "4685824" : 310,
            "4751360" : 320,
            "4816896" : 346,
            "4882432" : 362,
            "4947968" : 396,
            "5013504" : 422,
            "5079040" : 428,
            "5144576" : 442,
            "5210112" : 418,
            "5275648" : 472,
            "5341184" : 500,
            "5406720" : 514,
            "5472256" : 548,
            "5537792" : 540,
            "5603328" : 561,
            "5668864" : 630,
            "5734400" : 582,
            "5799936" : 630,
            "5865472" : 644,
            "5931008" : 647,
            "5996544" : 694,
            "6062080" : 714,
            "6127616" : 801,
            "6193152" : 739,
            "6258688" : 776,
            "6324224" : 791,
            "6389760" : 775,
            "6455296" : 810,
            "6520832" : 855,
            "6586368" : 845,
            "6651904" : 944,
            "6717440" : 891,
            "6782976" : 939,
            "6848512" : 883,
            "6914048" : 973,
            "6979584" : 997,
            "7045120" : 982,
            "7110656" : 1042,
            "7176192" : 1085,
            "7241728" : 1092,
            "7307264" : 1095,
            "7372800" : 1053,
            "7438336" : 1159,
            "7503872" : 1206,
            "7569408" : 1195,
            "7634944" : 1215,
            "7700480" : 1227,
            "7766016" : 1204,
            "7831552" : 1255,
            "7897088" : 1249,
            "7962624" : 1257,
            "8028160" : 1305,
            "8093696" : 1402,
            "8159232" : 1354,
            "8224768" : 1277,
            "8290304" : 1450,
            "8355840" : 1416,
            "8454144" : 2790,
            "8585216" : 2952,
            "8716288" : 3037,
            "8847360" : 3013,
            "8978432" : 2987,
            "9109504" : 3103,
            "9240576" : 3204,
            "9371648" : 3151,
            "9502720" : 3248,
            "9633792" : 3321,
            "9764864" : 3350,
            "9895936" : 3337,
            "10027008" : 3487,
            "10158080" : 3275,
            "10289152" : 3518,
            "10420224" : 3388,
            "10551296" : 3296,
            "10682368" : 3416,
            "10813440" : 3542,
            "10944512" : 3457,
            "11075584" : 3516,
            "11206656" : 3507,
            "11337728" : 3463,
            "11468800" : 3423,
            "11599872" : 3623,
            "11730944" : 3576,
            "11862016" : 3360,
            "11993088" : 3502,
            "12124160" : 3489,
            "12255232" : 3544,
            "12386304" : 3502,
            "12517376" : 3400,
            "12648448" : 3428,
            "12779520" : 3314,
            "12910592" : 3389,
            "13041664" : 3327,
            "13172736" : 3361,
            "13303808" : 3402,
            "13434880" : 3295,
            "13565952" : 3180,
            "13697024" : 3158,
            "13828096" : 3231,
            "13959168" : 3104,
            "14090240" : 3026,
            "14221312" : 3118,
            "14352384" : 3014,
            "14483456" : 2912,
            "14614528" : 2913,
            "14745600" : 2775,
            "14876672" : 2761,
            "15007744" : 2775,
            "15138816" : 2699,
            "15269888" : 2744,
            "15400960" : 2653,
            "15532032" : 2580,
            "15663104" : 2545,
            "15794176" : 2510,
            "15925248" : 2497,
            "16056320" : 2400,
            "16187392" : 2471,
            "16318464" : 2366,
            "16449536" : 2309,
            "16580608" : 2263,
            "16711680" : 2241,
            "16908288" : 4243,
            "17170432" : 4079,
            "17432576" : 3985,
            "17694720" : 3733,
            "17956864" : 3641,
            "18219008" : 3402,
            "18481152" : 3347,
            "18743296" : 3310,
            "19005440" : 3025,
            "19267584" : 2924,
            "19529728" : 2838,
            "19791872" : 2789,
            "20054016" : 2596,
            "20316160" : 2486,
            "20578304" : 2314,
            "20840448" : 2297,
            "21102592" : 2197,
            "21364736" : 2065,
            "21626880" : 1923,
            "21889024" : 1878,
            "22151168" : 1793,
            "22413312" : 1602,
            "22675456" : 1668,
            "22937600" : 1453,
            "23199744" : 1399,
            "23461888" : 1396,
            "23724032" : 1266,
            "23986176" : 1177,
            "24248320" : 1191,
            "24510464" : 1042,
            "24772608" : 1028,
            "25034752" : 953,
            "25296896" : 988,
            "25559040" : 896,
            "25821184" : 851,
            "26083328" : 805,
            "26345472" : 772,
            "26607616" : 704,
            "26869760" : 651,
            "27131904" : 643,
            "27394048" : 628,
            "27656192" : 568,
            "27918336" : 561,
            "28180480" : 490,
            "28442624" : 439,
            "28704768" : 448,
            "28966912" : 431,
            "29229056" : 359,
            "29491200" : 327,
            "29753344" : 363,
            "30015488" : 341,
            "30277632" : 307,
            "30539776" : 300,
            "30801920" : 245,
            "31064064" : 231,
            "31326208" : 231,
            "31588352" : 233,
            "31850496" : 203,
            "32112640" : 213,
            "32374784" : 155,
            "32636928" : 160,
            "32899072" : 161,
            "33161216" : 170,
            "33423360" : 138,
            "33816576" : 258,
            "34340864" : 251,
            "34865152" : 220,
            "35389440" : 212,
            "35913728" : 182,
            "36438016" : 146,
            "36962304" : 136,
            "37486592" : 106,
            "38010880" : 106,
            "38535168" : 89,
            "39059456" : 85,
            "39583744" : 65,
            "40108032" : 57,
            "40632320" : 62,
            "41156608" : 41,
            "41680896" : 45,
            "42205184" : 34,
            "42729472" : 41,
            "43253760" : 41,
            "43778048" : 43,
            "44302336" : 23,
            "44826624" : 22,
            "45350912" : 18,
            "45875200" : 14,
            "46399488" : 17,
            "46923776" : 15,
            "47448064" : 19,
            "47972352" : 11,
            "48496640" : 16,
            "49020928" : 8,
            "49545216" : 10,
            "50069504" : 9,
            "50593792" : 4,
            "51118080" : 7,
            "51642368" : 7,
            "52166656" : 3,
            "52690944" : 2,
            "53215232" : 3,
            "53739520" : 3,
            "54263808" : 2,
            "55836672" : 1
          }
        },
        "lat_ns" : {
          "min" : 252960,
          "max" : 55715113,
          "mean" : 13969767.688633,
          "stddev" : 5906304.991171
        },
        "bw_min" : 37544,
        "bw_max" : 137424,
        "bw_agg" : 49.995907,
        "bw_mean" : 82530.744167,
        "bw_dev" : 21669.506886,
        "bw_samples" : 2400,
        "iops_min" : 160,
        "iops_max" : 405,
        "iops_mean" : 287.158750,
        "iops_stddev" : 38.264663,
        "iops_samples" : 2400
      },
      "trim" : {
        "io_bytes" : 0,
        "io_kbytes" : 0,
        "bw_bytes" : 0,
        "bw" : 0,
        "iops" : 0.000000,
        "runtime" : 0,
        "total_ios" : 0,
        "short_ios" : 0,
        "drop_ios" : 0,
        "slat_ns" : {
          "min" : 0,
          "max" : 0,
          "mean" : 0.000000,
          "stddev" : 0.000000
        },
        "clat_ns" : {
          "min" : 0,
          "max" : 0,
          "mean" : 0.000000,
          "stddev" : 0.000000,
          "percentile" : {
            "1.000000" : 0,
            "5.000000" : 0,
            "10.000000" : 0,
            "20.000000" : 0,
            "30.000000" : 0,
            "40.000000" : 0,
            "50.000000" : 0,
            "60.000000" : 0,
            "70.000000" : 0,
            "80.000000" : 0,
            "90.000000" : 0,
            "95.000000" : 0,
            "99.000000" : 0,
            "99.500000" : 0,
            "99.900000" : 0,
            "99.950000" : 0,
            "99.990000" : 0
          },
          "bins" : {

          }
        },
        "lat_ns" : {
          "min" : 0,
          "max" : 0,
          "mean" : 0.000000,
          "stddev" : 0.000000
        },
        "bw_min" : 0,
        "bw_max" : 0,
        "bw_agg" : 0.000000,
        "bw_mean" : 0.000000,
        "bw_dev" : 0.000000,
        "bw_samples" : 0,
        "iops_min" : 0,
        "iops_max" : 0,
        "iops_mean" : 0.000000,
        "iops_stddev" : 0.000000,
        "iops_samples" : 0
      },
      "sync" : {
        "lat_ns" : {
          "min" : 0,
          "max" : 0,
          "mean" : 0.000000,
          "stddev" : 0.000000,
          "percentile" : {
            "1.000000" : 0,
            "5.000000" : 0,
            "10.000000" : 0,
            "20.000000" : 0,
            "30.000000" : 0,
            "40.000000" : 0,
            "50.000000" : 0,
            "60.000000" : 0,
            "70.000000" : 0,
            "80.000000" : 0,
            "90.000000" : 0,
            "95.000000" : 0,
            "99.000000" : 0,
            "99.500000" : 0,
            "99.900000" : 0,
            "99.950000" : 0,
            "99.990000" : 0
          },
          "bins" : {

          }
        },
        "total_ios" : 0
      },
      "job_runtime" : 1200021,
      "usr_cpu" : 1.966632,
      "sys_cpu" : 4.950247,
      "ctx" : 1693732,
      "majf" : 0,
      "minf" : 57472,
      "iodepth_level" : {
        "1" : 0.100000,
        "2" : 0.100000,
        "4" : 0.100000,
        "8" : 0.100000,
        "16" : 99.998870,
        "32" : 0.000000,
        ">=64" : 0.000000
      },
      "latency_ns" : {
        "2" : 0.000000,
        "4" : 0.000000,
        "10" : 0.000000,
        "20" : 0.000000,
        "50" : 0.000000,
        "100" : 0.000000,
        "250" : 0.000000,
        "500" : 0.000000,
        "750" : 0.000000,
        "1000" : 0.000000
      },
      "latency_us" : {
        "2" : 0.000000,
        "4" : 0.000000,
        "10" : 0.000000,
        "20" : 0.000000,
        "50" : 0.000000,
        "100" : 0.000000,
        "250" : 0.010000,
        "500" : 0.057260,
        "750" : 0.198638,
        "1000" : 0.475593
      },
      "latency_ms" : {
        "2" : 6.707243,
        "4" : 24.191642,
        "10" : 44.610217,
        "20" : 21.307831,
        "50" : 2.446227,
        "100" : 0.010000,
        "250" : 0.000000,
        "500" : 0.000000,
        "750" : 0.000000,
        "1000" : 0.000000,
        "2000" : 0.000000,
        ">=2000" : 0.000000
      },
      "latency_depth" : 16,
      "latency_target" : 0,
      "latency_percentile" : 100.000000,
      "latency_window" : 0
    }
  ],
  "disk_util" : [
    {
      "name" : "sdb",
      "read_ios" : 2309189,
      "write_ios" : 344519,
      "read_merges" : 0,
      "write_merges" : 0,
      "read_ticks" : 14284588,
      "write_ticks" : 4789180,
      "in_queue" : 19076344,
      "util" : 100.000000
    }
  ]
}
